lalsuite-7.26.1.data/scripts/lalpulsar_ComputeFstatLatticeCount
lalsuite-7.26.1.data/scripts/lalfr-cat
lalsuite-7.26.1.data/scripts/lalpulsar_spec_avg_long
lalsuite-7.26.1.data/scripts/lalapps_fr_ninja
lalsuite-7.26.1.data/scripts/lalinference_cpnest
lalsuite-7.26.1.data/scripts/lalburst_power_plot_binjtf
lalsuite-7.26.1.data/scripts/lalburst_cut
lalsuite-7.26.1.data/scripts/lalapps_fits_header_getval
lalsuite-7.26.1.data/scripts/lal_fftw_wisdom
lalsuite-7.26.1.data/scripts/lalburst_power_meas_likelihood
lalsuite-7.26.1.data/scripts/lalpulsar_synthesizeBstatMC
lalsuite-7.26.1.data/scripts/lalsim-ns-mass-radius
lalsuite-7.26.1.data/scripts/lalpulsar_version
lalsuite-7.26.1.data/scripts/lalapps_HierarchSearchGCT
lalsuite-7.26.1.data/scripts/lalapps_pulsar_parameter_estimation_nested
lalsuite-7.26.1.data/scripts/lalsim-ns-params
lalsuite-7.26.1.data/scripts/lalfr-split
lalsuite-7.26.1.data/scripts/lalapps_cbc_stochasticbank
lalsuite-7.26.1.data/scripts/lalsim-inspiral
lalsuite-7.26.1.data/scripts/lalpulsar_CopyPublicSFTs
lalsuite-7.26.1.data/scripts/lalapps_combine_crosscorr_toplists
lalsuite-7.26.1.data/scripts/lal_path2cache
lalsuite-7.26.1.data/scripts/lalapps_fftwf_wisdom
lalsuite-7.26.1.data/scripts/lalpulsar_SFTvalidate
lalsuite-7.26.1.data/scripts/lalinference_nest
lalsuite-7.26.1.data/scripts/lalapps_ComputeAntennaPattern
lalsuite-7.26.1.data/scripts/lalpulsar_MakeSFTs
lalsuite-7.26.1.data/scripts/lalpulsar_frequency_evolution
lalsuite-7.26.1.data/scripts/lalapps_blindinj
lalsuite-7.26.1.data/scripts/lalsim-bh-sphwf
lalsuite-7.26.1.data/scripts/lalapps_makeblindinj_himass
lalsuite-7.26.1.data/scripts/lalapps_WriteSFTsfromSFDBs
lalsuite-7.26.1.data/scripts/lal_version
lalsuite-7.26.1.data/scripts/lalapps_inspiralDistance
lalsuite-7.26.1.data/scripts/lalapps_synthesizeLVStats
lalsuite-7.26.1.data/scripts/lalinference_bench
lalsuite-7.26.1.data/scripts/lalapps_CopySFTs
lalsuite-7.26.1.dist-info/RECORD
lalsuite-7.26.1.dist-info/WHEEL
lalsuite-7.26.1.dist-info/top_level.txt
lalsuite-7.26.1.dist-info/METADATA
lalsuite-7.26.1.dist-info/licenses/COPYING
