Metadata-Version: 2.4
Name: lalsuite
Version: 7.26.1
Summary: LIGO Scientific Collaboration Algorithm Library - minimal Python package
Home-page: https://git.ligo.org/lscsoft/lalsuite
Author: LIGO Scientific Collaboration
Author-email: lal-discuss@ligo.org
Maintainer: Adam Mercer
Maintainer-email: adam.mercer@ligo.org
License: GPL-2+
Project-URL: Bug Tracker, https://git.ligo.org/lscsoft/lalsuite/-/issues/
Project-URL: Documentation, https://lscsoft.docs.ligo.org/lalsuite/
Project-URL: Source Code, https://git.ligo.org/lscsoft/lalsuite
Classifier: Development Status :: 5 - Production/Stable
Classifier: Intended Audience :: Science/Research
Classifier: License :: OSI Approved :: GNU General Public License v2 or later (GPLv2+)
Classifier: Operating System :: POSIX
Classifier: Natural Language :: English
Classifier: Programming Language :: Python :: 3
Classifier: Programming Language :: Python :: 3.7
Classifier: Programming Language :: Python :: 3.8
Classifier: Programming Language :: Python :: 3.9
Classifier: Programming Language :: Python :: 3.10
Classifier: Programming Language :: Python :: 3.11
Classifier: Programming Language :: Python :: 3.12
Classifier: Topic :: Scientific/Engineering
Classifier: Topic :: Scientific/Engineering :: Astronomy
Classifier: Topic :: Scientific/Engineering :: Physics
Requires-Python: >=3.9
License-File: COPYING
Requires-Dist: astropy
Requires-Dist: igwn-ligolw
Requires-Dist: igwn-segments
Requires-Dist: lscsoft-glue
Requires-Dist: matplotlib
Requires-Dist: numpy>=1.19
Requires-Dist: python-dateutil
Requires-Dist: scipy
Provides-Extra: lalinference
Requires-Dist: gwdatafind; extra == "lalinference"
Requires-Dist: gwpy; extra == "lalinference"
Requires-Dist: healpy>=1.9.1; extra == "lalinference"
Requires-Dist: scipy; extra == "lalinference"
Provides-Extra: lalpulsar
Requires-Dist: solar_system_ephemerides; extra == "lalpulsar"
Provides-Extra: test
Requires-Dist: pytest; extra == "test"
Dynamic: author
Dynamic: author-email
Dynamic: classifier
Dynamic: description
Dynamic: home-page
Dynamic: license
Dynamic: license-file
Dynamic: maintainer
Dynamic: maintainer-email
Dynamic: project-url
Dynamic: provides-extra
Dynamic: requires-dist
Dynamic: requires-python
Dynamic: summary
